dll_finder.py
dll_finder-1.0.dist-info/LICENSE
dll_finder-1.0.dist-info/METADATA
dll_finder-1.0.dist-info/WHEEL
dll_finder-1.0.dist-info/top_level.txt
dll_finder-1.0.dist-info/RECORD
