Metadata-Version: 2.1
Name: dll-finder
Version: 1.0
Summary: dll_finder
Home-page: https://github.com/brouhaha/dll_finder
Author: Eric Smith
Author-email: spacewar@gmail.com
Classifier: Programming Language :: Python
Classifier: Programming Language :: Python :: 3
Classifier: Programming Language :: Python :: 3.11
Classifier: Development Status :: 4 - Beta
Classifier: Environment :: Console
Classifier: Intended Audience :: Developers
Classifier: License :: OSI Approved :: GNU General Public License v3 (GPLv3)
Classifier: Operating System :: OS Independent
Classifier: Topic :: Software Development :: Assemblers
Requires-Python: >=3.11
License-File: LICENSE
Requires-Dist: pyparser
Requires-Dist: m5pre
